LICENSE.txt
MANIFEST.in
README.md
setup.py
megafeed/__init__.py
megafeed/megafeed.py
megafeed/middleware.py
megafeed/settings.py
megafeed/views.py
megafeed.egg-info/PKG-INFO
megafeed.egg-info/SOURCES.txt
megafeed.egg-info/dependency_links.txt
megafeed.egg-info/top_level.txt
megafeed/templatetags/__init__.py
megafeed/templatetags/megafeed_tags.py