Metadata-Version: 1.0
Name: megafeed
Version: v0.1.2
Summary: A library for serializing complex django querysets.
Home-page: http://www.github.com/ff0000/megafeed/
Author: RED Interactive Agency
Author-email: geeks@ff0000.com
License: MIT license
Download-URL: http://www.github.com/ff0000/megafeed/
Platform: UNKNOWN
Classifier: Development Status :: 4 - Beta
Classifier: Environment :: Web Environment
Classifier: Framework :: Django
Classifier: Intended Audience :: Developers
Classifier: License :: OSI Approved :: MIT License
Classifier: Natural Language :: English
Classifier: Programming Language :: Python
Classifier: Topic :: Internet :: WWW/HTTP :: Dynamic Content
